{
  "docketNumber": "84862-3",
  "docketNumberNormalized": "848623",
  "caseTitle": "State Of Washington, Respondent V. David M. Putman, Appellant",
  "fileDate": "2024-09-03",
  "fileContains": "Majority Opinion",
  "fileMonthSection": "September 2024",
  "courtLevel": "C",
  "publicationStatus": "UNP",
  "detailUrl": "https://www.courts.wa.gov/opinions/index.cfm?fa=opinions.showOpinion&filename=848623MAJ",
  "pdfUrl": "https://www.courts.wa.gov/opinions/pdf/848623.pdf",
  "htmlUrl": "https://www.courts.wa.gov/opinions/index.cfm?fa=opinions.showOpinion&filename=848623MAJ",
  "pdfPath": "data/wa-courts/court-of-appeals-slip-unpublished/2024/848623.pdf",
  "isRevised": false,
  "fetchedAt": "2025-10-31T04:21:54.121Z",
  "division": "I"
}