{
  "docketNumber": "85100-4",
  "docketNumberNormalized": "851004",
  "caseTitle": "Larry Campbell, App. V. At&t, Inc. And The Dept. Of Labor & Industries, Res.",
  "fileDate": "2024-03-04",
  "fileContains": "Majority Opinion",
  "fileMonthSection": "March 2024",
  "courtLevel": "C",
  "publicationStatus": "UNP",
  "detailUrl": "https://www.courts.wa.gov/opinions/index.cfm?fa=opinions.showOpinion&filename=851004MAJ",
  "pdfUrl": "https://www.courts.wa.gov/opinions/pdf/851004.pdf",
  "htmlUrl": "https://www.courts.wa.gov/opinions/index.cfm?fa=opinions.showOpinion&filename=851004MAJ",
  "pdfPath": "data/wa-courts/court-of-appeals-slip-unpublished/2024/851004.pdf",
  "isRevised": false,
  "fetchedAt": "2025-10-31T04:21:52.811Z",
  "division": "I"
}