{
  "docketNumber": "81282-3",
  "docketNumberNormalized": "812823",
  "caseTitle": "Meika Nowak, Respondent V. James Magee, Appellant",
  "fileDate": "2022-08-01",
  "fileContains": "Majority Opinion",
  "fileMonthSection": "August 2022",
  "courtLevel": "C",
  "publicationStatus": "UNP",
  "detailUrl": "https://www.courts.wa.gov/opinions/index.cfm?fa=opinions.showOpinion&filename=812823MAJ",
  "pdfUrl": "https://www.courts.wa.gov/opinions/pdf/812823.pdf",
  "htmlUrl": "https://www.courts.wa.gov/opinions/index.cfm?fa=opinions.showOpinion&filename=812823MAJ",
  "pdfPath": "data/wa-courts/court-of-appeals-slip-unpublished/2022/812823.pdf",
  "isRevised": false,
  "fetchedAt": "2025-10-31T04:52:39.525Z",
  "division": "I"
}