{
  "docketNumber": "82656-5",
  "docketNumberNormalized": "826565",
  "caseTitle": "Amir Sirous Najafabadi, Appellant V. Housing Authority Of Snohomish County, Respondent",
  "fileDate": "2022-08-08",
  "fileContains": "Majority Opinion",
  "fileMonthSection": "August 2022",
  "courtLevel": "C",
  "publicationStatus": "UNP",
  "detailUrl": "https://www.courts.wa.gov/opinions/index.cfm?fa=opinions.showOpinion&filename=826565MAJ",
  "pdfUrl": "https://www.courts.wa.gov/opinions/pdf/826565.pdf",
  "htmlUrl": "https://www.courts.wa.gov/opinions/index.cfm?fa=opinions.showOpinion&filename=826565MAJ",
  "pdfPath": "data/wa-courts/court-of-appeals-slip-unpublished/2022/826565.pdf",
  "isRevised": false,
  "fetchedAt": "2025-10-31T04:52:39.536Z",
  "division": "I"
}