{
  "docketNumber": "82839-8",
  "docketNumberNormalized": "828398",
  "caseTitle": "Tara Martin, Appellant V. Daniel Martin & Kristin Prust, Respondents",
  "fileDate": "2022-06-06",
  "fileContains": "Majority Opinion",
  "fileMonthSection": "June 2022",
  "courtLevel": "C",
  "publicationStatus": "UNP",
  "detailUrl": "https://www.courts.wa.gov/opinions/index.cfm?fa=opinions.showOpinion&filename=828398MAJ",
  "pdfUrl": "https://www.courts.wa.gov/opinions/pdf/828398.pdf",
  "htmlUrl": "https://www.courts.wa.gov/opinions/index.cfm?fa=opinions.showOpinion&filename=828398MAJ",
  "pdfPath": "data/wa-courts/court-of-appeals-slip-unpublished/2022/828398.pdf",
  "isRevised": false,
  "fetchedAt": "2025-10-31T04:52:39.423Z",
  "division": "I"
}