{
  "docketNumber": "81583-1",
  "docketNumberNormalized": "815831",
  "caseTitle": "Charles Wagner, Respondent V. Rene Zottolo, Appellant",
  "fileDate": "2021-09-27",
  "fileContains": "Majority Opinion and an Order",
  "fileMonthSection": "September 2021",
  "courtLevel": "C",
  "publicationStatus": "PAR",
  "detailUrl": "https://www.courts.wa.gov/opinions/index.cfm?fa=opinions.showOpinion&filename=815831MAJ",
  "pdfUrl": "https://www.courts.wa.gov/opinions/pdf/815831.pdf",
  "htmlUrl": "https://www.courts.wa.gov/opinions/index.cfm?fa=opinions.showOpinion&filename=815831MAJ",
  "pdfPath": "data/wa-courts/court-of-appeals-slip-partial/2021/815831.pdf",
  "isRevised": true,
  "fetchedAt": "2025-10-31T05:09:48.289Z",
  "division": "I"
}