{
  "fetchedAt": "2025-10-31T03:56:38.131Z",
  "groupCode": "ga",
  "groupName": "Rules of General Application",
  "setCode": "LLLT RPC",
  "setAbbreviation": "LLLT RPC",
  "setName": "Washington State Court Rules: Limited License Legal Technician Rules of Professional Conduct (LLLT RPC)",
  "sourceUrl": "https://www.courts.wa.gov/court_rules/?fa=court_rules.list&group=ga&set=LLLT%20RPC",
  "rules": [
    {
      "ruleNumber": "Washington State Court Rules: Limited License Legal Technician Rules of Professional Conduct (LLLT RPC) LLLT RPC Limited License Legal Technician Rules of Professional Conduct (LLLT RPC)",
      "title": "LLLT RPC",
      "category": null,
      "pdfUrl": "https://www.courts.wa.gov/court_rules/pdf/LLLTRPC/GA_LLLTRPC.pdf",
      "pdfPath": "data/wa-court-rules/pdf/ga/LLLT RPC/GA_LLLTRPC.pdf"
    },
    {
      "ruleNumber": "LLLT RPC",
      "title": "Limited License Legal Technician Rules of Professional Conduct (LLLT RPC)",
      "category": null,
      "pdfUrl": "https://www.courts.wa.gov/court_rules/pdf/LLLTRPC/GA_LLLTRPC.pdf",
      "pdfPath": "data/wa-court-rules/pdf/ga/LLLT RPC/GA_LLLTRPC.pdf"
    }
  ]
}