{
  "docketNumber": "38749-6",
  "docketNumberNormalized": "387496",
  "caseTitle": "State of Washington v. David Ray Brown",
  "fileDate": "2023-02-23",
  "fileContains": "Majority Opinion and an Order",
  "fileMonthSection": "February 2023",
  "courtLevel": "C",
  "publicationStatus": "PUB",
  "detailUrl": "https://www.courts.wa.gov/opinions/index.cfm?fa=opinions.showOpinion&filename=387496MAJ",
  "pdfUrl": "https://www.courts.wa.gov/opinions/pdf/387496_ord.pdf",
  "htmlUrl": "https://www.courts.wa.gov/opinions/index.cfm?fa=opinions.showOpinion&filename=387496MAJ",
  "pdfPath": "data/wa-courts/court-of-appeals-slip-published/2023/387496_ord.pdf",
  "isRevised": true,
  "fetchedAt": "2025-10-31T04:35:24.251Z",
  "division": "III"
}