{
  "docketNumber": "99452-8",
  "docketNumberNormalized": "994528",
  "caseTitle": "State v. Arbogast",
  "fileDate": "2022-03-31",
  "fileContains": "Maj., and Dis. Opinions",
  "fileMonthSection": "March 2022",
  "courtLevel": "S",
  "publicationStatus": "PUB",
  "detailUrl": "https://www.courts.wa.gov/opinions/index.cfm?fa=opinions.showOpinion&filename=994528MAJ",
  "pdfUrl": "https://www.courts.wa.gov/opinions/pdf/994528.pdf",
  "htmlUrl": "https://www.courts.wa.gov/opinions/index.cfm?fa=opinions.showOpinion&filename=994528MAJ",
  "pdfPath": "data/wa-courts/supreme-slip-published/2022/994528.pdf",
  "isRevised": true,
  "fetchedAt": "2025-10-31T04:47:50.679Z",
  "division": null
}