{
  "docketNumber": "77315-1",
  "docketNumberNormalized": "773151",
  "caseTitle": "In Re The Marriage Of: Leslie Orr, Appellant And Jeffrey Mccann, Respondent",
  "fileDate": "2019-03-04",
  "fileContains": "Majority Opinion",
  "fileMonthSection": "March 2019",
  "courtLevel": "C",
  "publicationStatus": "UNP",
  "detailUrl": "https://www.courts.wa.gov/opinions/index.cfm?fa=opinions.showOpinion&filename=773151MAJ",
  "pdfUrl": "https://www.courts.wa.gov/opinions/pdf/773151.pdf",
  "htmlUrl": "https://www.courts.wa.gov/opinions/index.cfm?fa=opinions.showOpinion&filename=773151MAJ",
  "pdfPath": "data/wa-courts/court-of-appeals-slip-unpublished/2019/773151.pdf",
  "isRevised": false,
  "fetchedAt": "2025-10-31T13:01:39.115Z",
  "division": "I"
}