{
  "docketNumber": "77969-9",
  "docketNumberNormalized": "779699",
  "caseTitle": "State Of Washington, Respondent V. Sheriff Jabang, Appellant",
  "fileDate": "2019-03-11",
  "fileContains": "Majority Opinion",
  "fileMonthSection": "March 2019",
  "courtLevel": "C",
  "publicationStatus": "UNP",
  "detailUrl": "https://www.courts.wa.gov/opinions/index.cfm?fa=opinions.showOpinion&filename=779699MAJ",
  "pdfUrl": "https://www.courts.wa.gov/opinions/pdf/779699.pdf",
  "htmlUrl": "https://www.courts.wa.gov/opinions/index.cfm?fa=opinions.showOpinion&filename=779699MAJ",
  "pdfPath": "data/wa-courts/court-of-appeals-slip-unpublished/2019/779699.pdf",
  "isRevised": false,
  "fetchedAt": "2025-10-31T13:01:39.287Z",
  "division": "I"
}