{
  "docketNumber": "51822-8",
  "docketNumberNormalized": "518228",
  "caseTitle": "State Of Washington, Respondent V Arkangel D. Howard, Appellant",
  "fileDate": "2020-12-08",
  "fileContains": "Majority Opinion",
  "fileMonthSection": "December 2020",
  "courtLevel": "C",
  "publicationStatus": "PAR",
  "detailUrl": "https://www.courts.wa.gov/opinions/index.cfm?fa=opinions.showOpinion&filename=518228MAJ",
  "pdfUrl": "https://www.courts.wa.gov/opinions/pdf/D2%2051822-8-II%20Published%20Opinion.pdf",
  "htmlUrl": "https://www.courts.wa.gov/opinions/index.cfm?fa=opinions.showOpinion&filename=518228MAJ",
  "pdfPath": "data/wa-courts/court-of-appeals-slip-partial/2020/D2%2051822-8-II%20Published%20Opinion.pdf",
  "isRevised": true,
  "fetchedAt": "2025-10-31T05:26:40.072Z",
  "division": "II"
}