{
  "docketNumber": "36423-2",
  "docketNumberNormalized": "364232",
  "caseTitle": "In the Matter of the Parental Rights to: D.J.S.",
  "fileDate": "2020-01-28",
  "fileContains": "Majority Opinion",
  "fileMonthSection": "January 2020",
  "courtLevel": "C",
  "publicationStatus": "PUB",
  "detailUrl": "https://www.courts.wa.gov/opinions/index.cfm?fa=opinions.showOpinion&filename=364232MAJ",
  "pdfUrl": "https://www.courts.wa.gov/opinions/pdf/364232_pub.pdf",
  "htmlUrl": "https://www.courts.wa.gov/opinions/index.cfm?fa=opinions.showOpinion&filename=364232MAJ",
  "pdfPath": "data/wa-courts/court-of-appeals-slip-published/2020/364232_pub.pdf",
  "isRevised": true,
  "fetchedAt": "2025-10-31T05:23:47.433Z",
  "division": "III"
}