{
  "docketNumber": "80656-4",
  "docketNumberNormalized": "806564",
  "caseTitle": "State Of Washington, Respondent V. Patrick Maulolo, Appellant",
  "fileDate": "2021-03-01",
  "fileContains": "Majority Opinion",
  "fileMonthSection": "March 2021",
  "courtLevel": "C",
  "publicationStatus": "UNP",
  "detailUrl": "https://www.courts.wa.gov/opinions/index.cfm?fa=opinions.showOpinion&filename=806564MAJ",
  "pdfUrl": "https://www.courts.wa.gov/opinions/pdf/806564.pdf",
  "htmlUrl": "https://www.courts.wa.gov/opinions/index.cfm?fa=opinions.showOpinion&filename=806564MAJ",
  "pdfPath": "data/wa-courts/court-of-appeals-slip-unpublished/2021/806564.pdf",
  "isRevised": false,
  "fetchedAt": "2025-10-31T05:10:14.373Z",
  "division": "I"
}