{
  "docketNumber": "82764-2",
  "docketNumberNormalized": "827642",
  "caseTitle": "State Of Washington, Respondent V. Seth Tyrone Crum, Appellant",
  "fileDate": "2021-10-11",
  "fileContains": "Majority Opinion",
  "fileMonthSection": "October 2021",
  "courtLevel": "C",
  "publicationStatus": "UNP",
  "detailUrl": "https://www.courts.wa.gov/opinions/index.cfm?fa=opinions.showOpinion&filename=827642MAJ",
  "pdfUrl": "https://www.courts.wa.gov/opinions/pdf/827642.pdf",
  "htmlUrl": "https://www.courts.wa.gov/opinions/index.cfm?fa=opinions.showOpinion&filename=827642MAJ",
  "pdfPath": "data/wa-courts/court-of-appeals-slip-unpublished/2021/827642.pdf",
  "isRevised": false,
  "fetchedAt": "2025-10-31T05:10:14.881Z",
  "division": "I"
}