{
  "docketNumber": "80956-3",
  "docketNumberNormalized": "809563",
  "caseTitle": "State Of Washington, Respondent V. Jarrell Cortez Davis, Appellant",
  "fileDate": "2021-04-26",
  "fileContains": "Majority Opinion",
  "fileMonthSection": "April 2021",
  "courtLevel": "C",
  "publicationStatus": "PUB",
  "detailUrl": "https://www.courts.wa.gov/opinions/index.cfm?fa=opinions.showOpinion&filename=809563MAJ",
  "pdfUrl": "https://www.courts.wa.gov/opinions/pdf/809563.pdf",
  "htmlUrl": "https://www.courts.wa.gov/opinions/index.cfm?fa=opinions.showOpinion&filename=809563MAJ",
  "pdfPath": "data/wa-courts/court-of-appeals-slip-published/2021/809563.pdf",
  "isRevised": true,
  "fetchedAt": "2025-10-31T05:05:58.178Z",
  "division": "I"
}