{
  "docketNumber": "38017-3",
  "docketNumberNormalized": "380173",
  "caseTitle": "Joann Caskey v. Old Republic Surety Co.",
  "fileDate": "2022-03-17",
  "fileContains": "Majority Opinion",
  "fileMonthSection": null,
  "courtLevel": "C",
  "publicationStatus": "PUB",
  "detailUrl": "https://www.courts.wa.gov/opinions/index.cfm?fa=opinions.showOpinion&filename=380173MAJ",
  "pdfUrl": "https://www.courts.wa.gov/opinions/pdf/380173_pub.pdf",
  "htmlUrl": "https://www.courts.wa.gov/opinions/index.cfm?fa=opinions.showOpinion&filename=380173MAJ",
  "pdfPath": "data/wa-courts/court-of-appeals-slip-published/2022/380173_pub.pdf",
  "isRevised": true,
  "fetchedAt": "2025-10-31T04:49:14.473Z",
  "division": "III"
}