{
  "docketNumber": "55881-5",
  "docketNumberNormalized": "558815",
  "caseTitle": "State Of Washington, Respondent V. Randy Gene Richter, Appellant",
  "fileDate": "2022-12-13",
  "fileContains": "Maj., and Con. Opinions",
  "fileMonthSection": null,
  "courtLevel": "C",
  "publicationStatus": "PUB",
  "detailUrl": "https://www.courts.wa.gov/opinions/index.cfm?fa=opinions.showOpinion&filename=558815MAJ",
  "pdfUrl": "https://www.courts.wa.gov/opinions/pdf/D2%2055881-5-II%20Published%20Opinion.pdf",
  "htmlUrl": "https://www.courts.wa.gov/opinions/index.cfm?fa=opinions.showOpinion&filename=558815MAJ",
  "pdfPath": "data/wa-courts/court-of-appeals-slip-published/2022/D2%2055881-5-II%20Published%20Opinion.pdf",
  "isRevised": true,
  "fetchedAt": "2025-10-31T04:49:14.672Z",
  "division": "II"
}