{
  "docketNumber": "39499-9",
  "docketNumberNormalized": "394999",
  "caseTitle": "State of Washington v. Shaun Aaron Schlenker",
  "fileDate": "2024-08-08",
  "fileContains": "Majority Opinion and an Order",
  "fileMonthSection": "August 2024",
  "courtLevel": "C",
  "publicationStatus": "PUB",
  "detailUrl": "https://www.courts.wa.gov/opinions/index.cfm?fa=opinions.showOpinion&filename=394999MAJ",
  "pdfUrl": "https://www.courts.wa.gov/opinions/pdf/394999_%20ord.pdf",
  "htmlUrl": "https://www.courts.wa.gov/opinions/index.cfm?fa=opinions.showOpinion&filename=394999MAJ",
  "pdfPath": "data/wa-courts/court-of-appeals-slip-published/2024/394999_%20ord.pdf",
  "isRevised": true,
  "fetchedAt": "2025-10-31T04:18:04.876Z",
  "division": "III"
}