{
  "docketNumber": "39571-5",
  "docketNumberNormalized": "395715",
  "caseTitle": "Sarah Nunley, et al v. Chelan-Douglas Health District",
  "fileDate": "2024-10-31",
  "fileContains": "Majority Opinion",
  "fileMonthSection": "October 2024",
  "courtLevel": "C",
  "publicationStatus": "PUB",
  "detailUrl": "https://www.courts.wa.gov/opinions/index.cfm?fa=opinions.showOpinion&filename=395715MAJ",
  "pdfUrl": "https://www.courts.wa.gov/opinions/pdf/395715_pub.pdf",
  "htmlUrl": "https://www.courts.wa.gov/opinions/index.cfm?fa=opinions.showOpinion&filename=395715MAJ",
  "pdfPath": "data/wa-courts/court-of-appeals-slip-published/2024/395715_pub.pdf",
  "isRevised": true,
  "fetchedAt": "2025-10-31T04:18:05.042Z",
  "division": "III"
}