{
  "docketNumber": "58214-7",
  "docketNumberNormalized": "582147",
  "caseTitle": "City Of Vancouver, Respondent V. Michael Joshua Moseley, Appellant",
  "fileDate": "2025-03-04",
  "fileContains": "Majority Opinion",
  "fileMonthSection": "March 2025",
  "courtLevel": "C",
  "publicationStatus": "UNP",
  "detailUrl": "https://www.courts.wa.gov/opinions/index.cfm?fa=opinions.showOpinion&filename=582147MAJ",
  "pdfUrl": "https://www.courts.wa.gov/opinions/pdf/D2%2058214-7-II%20Unpublished%20Opinion.pdf",
  "htmlUrl": "https://www.courts.wa.gov/opinions/index.cfm?fa=opinions.showOpinion&filename=582147MAJ",
  "pdfPath": "data/wa-courts/court-of-appeals-slip-unpublished/2025/D2%2058214-7-II%20Unpublished%20Opinion.pdf",
  "isRevised": false,
  "fetchedAt": "2025-10-31T04:05:15.600Z",
  "division": "II"
}