{
  "docketNumber": "59013-1",
  "docketNumberNormalized": "590131",
  "caseTitle": "State of Washington, Respondent v. Matthew Howard Smith, Appellant",
  "fileDate": "2025-09-03",
  "fileContains": "Majority Opinion",
  "fileMonthSection": "September 2025",
  "courtLevel": "C",
  "publicationStatus": "UNP",
  "detailUrl": "https://www.courts.wa.gov/opinions/index.cfm?fa=opinions.showOpinion&filename=590131MAJ",
  "pdfUrl": "https://www.courts.wa.gov/opinions/pdf/D2%2059013-1-II%20Unpublished%20Opinion.pdf",
  "htmlUrl": "https://www.courts.wa.gov/opinions/index.cfm?fa=opinions.showOpinion&filename=590131MAJ",
  "pdfPath": "data/wa-courts/court-of-appeals-slip-unpublished/2025/D2%2059013-1-II%20Unpublished%20Opinion.pdf",
  "isRevised": false,
  "fetchedAt": "2025-10-31T04:05:16.251Z",
  "division": "II"
}