{
  "docketNumber": "86399-1",
  "docketNumberNormalized": "863991",
  "caseTitle": "In Re Marriage Of Marc Coluccio, Respondent, And Ilyana Khanlarova, Appellant",
  "fileDate": "2025-10-20",
  "fileContains": "Majority Opinion",
  "fileMonthSection": "October 2025",
  "courtLevel": "C",
  "publicationStatus": "UNP",
  "detailUrl": "https://www.courts.wa.gov/opinions/index.cfm?fa=opinions.showOpinion&filename=863991MAJ",
  "pdfUrl": "https://www.courts.wa.gov/opinions/pdf/863991.pdf",
  "htmlUrl": "https://www.courts.wa.gov/opinions/index.cfm?fa=opinions.showOpinion&filename=863991MAJ",
  "pdfPath": "data/wa-courts/court-of-appeals-slip-unpublished/2025/863991.pdf",
  "isRevised": false,
  "fetchedAt": "2025-10-31T04:05:16.391Z",
  "division": "I"
}