{
  "docketNumber": "87485-3",
  "docketNumberNormalized": "874853",
  "caseTitle": "Bangorn Sayaseng, Et Al, Respondent V. Geodis Logistics, Llc., Appellant",
  "fileDate": "2025-09-29",
  "fileContains": "Majority Opinion",
  "fileMonthSection": "September 2025",
  "courtLevel": "C",
  "publicationStatus": "UNP",
  "detailUrl": "https://www.courts.wa.gov/opinions/index.cfm?fa=opinions.showOpinion&filename=874853MAJ",
  "pdfUrl": "https://www.courts.wa.gov/opinions/pdf/874853.pdf",
  "htmlUrl": "https://www.courts.wa.gov/opinions/index.cfm?fa=opinions.showOpinion&filename=874853MAJ",
  "pdfPath": "data/wa-courts/court-of-appeals-slip-unpublished/2025/874853.pdf",
  "isRevised": false,
  "fetchedAt": "2025-10-31T04:05:16.302Z",
  "division": "I"
}