{
  "docketNumber": "95394-5",
  "docketNumberNormalized": "953945",
  "caseTitle": "In re Pers. Restraint Petition of Meippen",
  "fileDate": "2019-05-09",
  "fileContains": "Maj., and Dis. Opinions",
  "fileMonthSection": "May 2019",
  "courtLevel": "S",
  "publicationStatus": "PUB",
  "detailUrl": "https://www.courts.wa.gov/opinions/index.cfm?fa=opinions.showOpinion&filename=953945MAJ",
  "pdfUrl": "https://www.courts.wa.gov/opinions/pdf/953945.pdf",
  "htmlUrl": "https://www.courts.wa.gov/opinions/index.cfm?fa=opinions.showOpinion&filename=953945MAJ",
  "pdfPath": "data/wa-courts/supreme-slip-published/2019/953945.pdf",
  "isRevised": true,
  "fetchedAt": "2025-10-31T12:56:17.498Z",
  "division": null
}