{
  "docketNumber": "95586-7",
  "docketNumberNormalized": "955867",
  "caseTitle": "Thurston County v. City of Olympia",
  "fileDate": "2019-03-14",
  "fileContains": "Majority Opinion",
  "fileMonthSection": "March 2019",
  "courtLevel": "S",
  "publicationStatus": "PUB",
  "detailUrl": "https://www.courts.wa.gov/opinions/index.cfm?fa=opinions.showOpinion&filename=955867MAJ",
  "pdfUrl": "https://www.courts.wa.gov/opinions/pdf/95586-7.pdf",
  "htmlUrl": "https://www.courts.wa.gov/opinions/index.cfm?fa=opinions.showOpinion&filename=955867MAJ",
  "pdfPath": "data/wa-courts/supreme-slip-published/2019/95586-7.pdf",
  "isRevised": true,
  "fetchedAt": "2025-10-31T12:56:17.453Z",
  "division": null
}