{
  "docketNumber": "36378-3",
  "docketNumberNormalized": "363783",
  "caseTitle": "State of Washington v. Tim Allen Loe",
  "fileDate": "2020-04-28",
  "fileContains": "Majority Opinion",
  "fileMonthSection": "April 2020",
  "courtLevel": "C",
  "publicationStatus": "UNP",
  "detailUrl": "https://www.courts.wa.gov/opinions/index.cfm?fa=opinions.showOpinion&filename=363783MAJ",
  "pdfUrl": "https://www.courts.wa.gov/opinions/pdf/363783_unp.pdf",
  "htmlUrl": "https://www.courts.wa.gov/opinions/index.cfm?fa=opinions.showOpinion&filename=363783MAJ",
  "pdfPath": "data/wa-courts/court-of-appeals-slip-unpublished/2020/363783_unp.pdf",
  "isRevised": false,
  "fetchedAt": "2025-10-31T05:27:08.519Z",
  "division": "III"
}