{
  "docketNumber": "36867-0",
  "docketNumberNormalized": "368670",
  "caseTitle": "State of Washington v. Isaac Shane Sprauer",
  "fileDate": "2020-05-12",
  "fileContains": "Majority Opinion",
  "fileMonthSection": "May 2020",
  "courtLevel": "C",
  "publicationStatus": "UNP",
  "detailUrl": "https://www.courts.wa.gov/opinions/index.cfm?fa=opinions.showOpinion&filename=368670MAJ",
  "pdfUrl": "https://www.courts.wa.gov/opinions/pdf/368670_unp.pdf",
  "htmlUrl": "https://www.courts.wa.gov/opinions/index.cfm?fa=opinions.showOpinion&filename=368670MAJ",
  "pdfPath": "data/wa-courts/court-of-appeals-slip-unpublished/2020/368670_unp.pdf",
  "isRevised": false,
  "fetchedAt": "2025-10-31T05:27:08.547Z",
  "division": "III"
}