{
  "docketNumber": "51987-9",
  "docketNumberNormalized": "519879",
  "caseTitle": "Brian Cortland, Appellant/cross Respondent V. Lewis County, Respondent/cross Appellant",
  "fileDate": "2020-02-04",
  "fileContains": "Majority Opinion",
  "fileMonthSection": "February 2020",
  "courtLevel": "C",
  "publicationStatus": "UNP",
  "detailUrl": "https://www.courts.wa.gov/opinions/index.cfm?fa=opinions.showOpinion&filename=519879MAJ",
  "pdfUrl": "https://www.courts.wa.gov/opinions/pdf/D2%2051987-9-II%20Unpublished%20Opinion.pdf",
  "htmlUrl": "https://www.courts.wa.gov/opinions/index.cfm?fa=opinions.showOpinion&filename=519879MAJ",
  "pdfPath": "data/wa-courts/court-of-appeals-slip-unpublished/2020/D2%2051987-9-II%20Unpublished%20Opinion.pdf",
  "isRevised": false,
  "fetchedAt": "2025-10-31T05:27:08.213Z",
  "division": "II"
}