{
  "docketNumber": "51998-4",
  "docketNumberNormalized": "519984",
  "caseTitle": "State Of Washington, Respondent V. Danika Lightle, Appellant",
  "fileDate": "2020-02-19",
  "fileContains": "Majority Opinion",
  "fileMonthSection": "February 2020",
  "courtLevel": "C",
  "publicationStatus": "UNP",
  "detailUrl": "https://www.courts.wa.gov/opinions/index.cfm?fa=opinions.showOpinion&filename=519984MAJ",
  "pdfUrl": "https://www.courts.wa.gov/opinions/pdf/D2%2051998-4-II%20Unpublished%20Opinion.pdf",
  "htmlUrl": "https://www.courts.wa.gov/opinions/index.cfm?fa=opinions.showOpinion&filename=519984MAJ",
  "pdfPath": "data/wa-courts/court-of-appeals-slip-unpublished/2020/D2%2051998-4-II%20Unpublished%20Opinion.pdf",
  "isRevised": false,
  "fetchedAt": "2025-10-31T05:27:08.256Z",
  "division": "II"
}