{
  "docketNumber": "52115-6",
  "docketNumberNormalized": "521156",
  "caseTitle": "State Of Washington, Respondent V. Donald Howard Mcelfish, Appellant",
  "fileDate": "2020-03-17",
  "fileContains": "Majority Opinion",
  "fileMonthSection": "March 2020",
  "courtLevel": "C",
  "publicationStatus": "UNP",
  "detailUrl": "https://www.courts.wa.gov/opinions/index.cfm?fa=opinions.showOpinion&filename=521156MAJ",
  "pdfUrl": "https://www.courts.wa.gov/opinions/pdf/D2%2052115-6-II%20Unpublished%20Opinion.pdf",
  "htmlUrl": "https://www.courts.wa.gov/opinions/index.cfm?fa=opinions.showOpinion&filename=521156MAJ",
  "pdfPath": "data/wa-courts/court-of-appeals-slip-unpublished/2020/D2%2052115-6-II%20Unpublished%20Opinion.pdf",
  "isRevised": false,
  "fetchedAt": "2025-10-31T05:27:08.373Z",
  "division": "II"
}