{
  "docketNumber": "78994-5",
  "docketNumberNormalized": "789945",
  "caseTitle": "Personal Restraint Petition Of Ricky Deshawn King",
  "fileDate": "2020-06-22",
  "fileContains": "Majority Opinion",
  "fileMonthSection": "June 2020",
  "courtLevel": "C",
  "publicationStatus": "UNP",
  "detailUrl": "https://www.courts.wa.gov/opinions/index.cfm?fa=opinions.showOpinion&filename=789945MAJ",
  "pdfUrl": "https://www.courts.wa.gov/opinions/pdf/789945.pdf",
  "htmlUrl": "https://www.courts.wa.gov/opinions/index.cfm?fa=opinions.showOpinion&filename=789945MAJ",
  "pdfPath": "data/wa-courts/court-of-appeals-slip-unpublished/2020/789945.pdf",
  "isRevised": false,
  "fetchedAt": "2025-10-31T05:27:08.629Z",
  "division": "I"
}