{
  "docketNumber": "79993-2",
  "docketNumberNormalized": "799932",
  "caseTitle": "In Re: A.j.b., Makis Brooks, App V. Krystal Link, Resp",
  "fileDate": "2020-06-15",
  "fileContains": "Majority Opinion",
  "fileMonthSection": "June 2020",
  "courtLevel": "C",
  "publicationStatus": "UNP",
  "detailUrl": "https://www.courts.wa.gov/opinions/index.cfm?fa=opinions.showOpinion&filename=799932MAJ",
  "pdfUrl": "https://www.courts.wa.gov/opinions/pdf/799932.pdf",
  "htmlUrl": "https://www.courts.wa.gov/opinions/index.cfm?fa=opinions.showOpinion&filename=799932MAJ",
  "pdfPath": "data/wa-courts/court-of-appeals-slip-unpublished/2020/799932.pdf",
  "isRevised": false,
  "fetchedAt": "2025-10-31T05:27:08.608Z",
  "division": "I"
}